reddit2ebook/__init__.py
reddit2ebook/base.css
reddit2ebook/main.py
reddit2ebook/ebooklib/__init__.py
reddit2ebook/ebooklib/epub.py
reddit2ebook/ebooklib/utils.py
reddit2ebook/ebooklib/plugins/__init__.py
reddit2ebook/ebooklib/plugins/base.py
reddit2ebook/ebooklib/plugins/booktype.py
reddit2ebook/ebooklib/plugins/sourcecode.py
reddit2ebook/ebooklib/plugins/standard.py
reddit2ebook/ebooklib/plugins/tidyhtml.py
reddit2ebook/ebooklib_patched/__init__.py
reddit2ebook/ebooklib_patched/epub.py
reddit2ebook/ebooklib_patched/utils.py
reddit2ebook/ebooklib_patched/plugins/__init__.py
reddit2ebook/ebooklib_patched/plugins/base.py
reddit2ebook/ebooklib_patched/plugins/booktype.py
reddit2ebook/ebooklib_patched/plugins/sourcecode.py
reddit2ebook/ebooklib_patched/plugins/standard.py
reddit2ebook/ebooklib_patched/plugins/tidyhtml.py
reddit2ebook-2.0.0.dist-info/DESCRIPTION.rst
reddit2ebook-2.0.0.dist-info/METADATA
reddit2ebook-2.0.0.dist-info/RECORD
reddit2ebook-2.0.0.dist-info/WHEEL
reddit2ebook-2.0.0.dist-info/entry_points.txt
reddit2ebook-2.0.0.dist-info/metadata.json
reddit2ebook-2.0.0.dist-info/top_level.txt
