Metadata-Version: 2.0
Name: reddit2ebook
Version: 2.0.0
Summary: convert reddit stories and comments into ebooks
Home-page: https://github.com/MissingNoIOI/reddit2ebook
Author: Gerrit Helling
Author-email: gerrit@akuma.pictures
License: GPLv3
Keywords: reddit ebook epub offline
Platform: UNKNOWN
Classifier: Development Status :: 4 - Beta
Classifier: Environment :: Console
Classifier: Intended Audience :: End Users/Desktop
Classifier: Topic :: Multimedia
Classifier: License :: OSI Approved :: GNU General Public License v3 (GPLv3)
Classifier: Operating System :: OS Independent
Classifier: Programming Language :: Python :: 3
Classifier: Programming Language :: Python :: 3.2
Classifier: Programming Language :: Python :: 3.3
Classifier: Programming Language :: Python :: 3.4
Classifier: Programming Language :: Python :: 3.5
Requires-Dist: Pillow
Requires-Dist: PyYaml
Requires-Dist: mistune
Requires-Dist: praw
Requires-Dist: pyprind
Requires-Dist: pypub
